Yuci_Dictionary-0.1.5.dist-info/METADATA
Yuci_Dictionary-0.1.5.dist-info/RECORD
Yuci_Dictionary-0.1.5.dist-info/WHEEL
Yuci_Dictionary-0.1.5.dist-info/entry_points.txt
Yuci_Dictionary-0.1.5.dist-info/top_level.txt
dictionary/__init__.py
dictionary/argument.py
dictionary/error_handler.py
dictionary/history.py
dictionary/youdao_dict.py
