Metadata-Version: 2.1
Name: Yuci-Dictionary
Version: 0.1.5
Summary: A tiny CLI dictionary built by python, based on youdao-web dictionary and require an internet connection.
Home-page: https://github.com/Yucklys/yuci-dictionary
Author: Yucklys
Author-email: yucklys687@outlook.com
License: MIT
Keywords: python youdao terminal
Platform: UNKNOWN
Classifier: License :: OSI Approved :: MIT License
Classifier: Operating System :: OS Independent
Requires-Dist: beautifulsoup4 (>=4.6.0)
Requires-Dist: lxml (>=4.0.0)
